YouTer/__init__.py
YouTer/__main__.py
YouTer/winds/__init__.py
YouTer/winds/about_w.py
YouTer/winds/custom_command.py
YouTer/winds/main_w.py
YouTer/winds/options_w.py
YouTer/winds/class_templates/__init__.py
YouTer/winds/class_templates/program_class.py
YouTer/winds/download_windows/__init__.py
YouTer/winds/download_windows/link_w.py
YouTer/winds/download_windows/youtubedl-w.py
YouTer/winds/download_windows/youtubedl_w.py
YouTer/winds/download_windows/audio_winds/__init__.py
YouTer/winds/download_windows/audio_winds/download_audio_w.py
YouTer/winds/download_windows/save_winds/__init__.py
YouTer/winds/download_windows/save_winds/other_save_w.py
YouTer/winds/download_windows/save_winds/save_w.py
YouTer/winds/download_windows/video_winds/__init__.py
YouTer/winds/download_windows/video_winds/download_video_w.py
YouTer/winds/download_windows/video_winds/specific_quality_w.py
YouTer-1.0.7.dist-info/LICENSE.md
YouTer-1.0.7.dist-info/METADATA
YouTer-1.0.7.dist-info/WHEEL
YouTer-1.0.7.dist-info/entry_points.txt
YouTer-1.0.7.dist-info/top_level.txt
YouTer-1.0.7.dist-info/RECORD
