Metadata-Version: 2.1
Name: YouTer
Version: 1.0.7
Summary: Terminal based gui program that downloads youtube videos in mp4 or mp3 formats.
Home-page: UNKNOWN
Author: Asley R.
Author-email: asleyrobleto@gmail.com
License: UNKNOWN
Keywords: python,video,audio,download,terminal
Platform: UNKNOWN
Classifier: Development Status :: 1 - Planning
Classifier: Intended Audience :: Developers
Classifier: Programming Language :: Python :: 3
Classifier: Operating System :: Unix
Classifier: Operating System :: MacOS :: MacOS X
Classifier: Operating System :: Microsoft :: Windows
Requires-Dist: youtube-dl
Requires-Dist: ffmpeg
Requires-Dist: numpy
